Metadata-Version: 2.1
Name: hoogberta
Version: 0.1.1
Summary: HoogBERTa: Multi-task Sequence Labeling using Thai Pretrained Language Representation
Home-page: https://github.com/lstnlp/HoogBERTa
Author: Peerachet Porkaew
Author-email: peerachet.porkaew@nectec.or.th
License: MIT
Download-URL: https://github.com/lstnlp/HoogBERTa/archive/refs/tags/v0.1.1.tar.gz
Keywords: HoogBERTa: Multi-task Sequence Labeling using Thai Pretrained Language Representation
Platform: UNKNOWN
Classifier: Development Status :: 3 - Alpha
Classifier: Intended Audience :: Developers
Classifier: Topic :: Scientific/Engineering :: Artificial Intelligence
Classifier: Topic :: Text Processing
Classifier: Topic :: Text Processing :: General
Classifier: License :: OSI Approved :: MIT License
Classifier: Programming Language :: Python :: 3
Classifier: Programming Language :: Python :: 3.6
Classifier: Programming Language :: Python :: 3.8
Classifier: Programming Language :: Python :: 3.9
